{
    "REF": {
        "obs": {
            "defaultReference": {
                "NAM": {
                    "DJF": {
                        "frac": 0.27189841706340206,
                        "stdv_pc": 1.530794779337859
                    },
                    "JJA": {
                        "frac": 0.17573866103232577,
                        "stdv_pc": 0.5855111929820276
                    },
                    "MAM": {
                        "frac": 0.22518714418093447,
                        "stdv_pc": 0.9736528524302126
                    },
                    "SON": {
                        "frac": 0.16145491224561526,
                        "stdv_pc": 0.736726646767106
                    }
                },
                "reference_eof_mode": 1,
                "source": "/work/lee1043/DATA/reanalysis/20CR/slp_monthly_mean/monthly.prmsl.1871-2012.nc"
            }
        }
    },
    "RESULTS": {
        "GFDL-CM3": {
            "c1": {
                "defaultReference": {
                    "NAM": {
                        "DJF": {
                            "bias_cbf": -0.0008193422187852191,
                            "bias_cbf_glo": 0.052234842325052294,
                            "bias_eof": -0.0008896733877497124,
                            "bias_eof_glo": 0.02090438653018814,
                            "cor_cbf": 0.9335764857946539,
                            "cor_cbf_glo": 0.9159791503107213,
                            "cor_eof": 0.9169666729559103,
                            "cor_eof_glo": 0.9027900634622247,
                            "frac_cbf": 0.3737711223978083,
                            "frac_eof": 0.3783755382915713,
                            "rms_cbf": 0.8255510693089279,
                            "rms_cbf_glo": 0.5211410877294853,
                            "rms_eof": 0.8986387408932641,
                            "rms_eof_glo": 0.5512396616525004,
                            "rmsc_cbf": 0.8255506627187956,
                            "rmsc_cbf_glo": 0.5185166868743455,
                            "rmsc_eof": 0.898638300494417,
                            "rmsc_eof_glo": 0.5508431457343911,
                            "stdv_cbf_pc": 1.9101124505406422,
                            "stdv_eof_pc": 2.068798777736043,
                            "stdv_pc_ratio_cbf_over_obs": 1.2477913279576613,
                            "stdv_pc_ratio_eof_over_obs": 1.3514540326763436,
                            "tcor_cbf_vs_eof_pc": 0.990312569484882
                        },
                        "JJA": {
                            "bias_cbf": -0.00012411696928704612,
                            "bias_cbf_glo": -0.004323056589346397,
                            "bias_eof": -9.576036911384022e-05,
                            "bias_eof_glo": 0.004592757138645029,
                            "cor_cbf": 0.9481891792286893,
                            "cor_cbf_glo": 0.8470224455492722,
                            "cor_eof": 0.933248171487302,
                            "cor_eof_glo": 0.83785318016428,
                            "frac_cbf": 0.23485136751538432,
                            "frac_eof": 0.2352109540240124,
                            "rms_cbf": 0.23647654185256947,
                            "rms_cbf_glo": 0.24317058151420706,
                            "rms_eof": 0.26401339871275764,
                            "rms_eof_glo": 0.2513064157421573,
                            "rmsc_cbf": 0.23647650928057942,
                            "rmsc_cbf_glo": 0.2431321510941795,
                            "rmsc_eof": 0.2640133813461228,
                            "rmsc_eof_glo": 0.2512644447092255,
                            "stdv_cbf_pc": 0.6648517183796622,
                            "stdv_eof_pc": 0.708801945383277,
                            "stdv_pc_ratio_cbf_over_obs": 1.1355064196015634,
                            "stdv_pc_ratio_eof_over_obs": 1.2105694201563006,
                            "tcor_cbf_vs_eof_pc": 0.9910032958424217
                        },
                        "MAM": {
                            "bias_cbf": -0.0004911156826598771,
                            "bias_cbf_glo": 0.01800855068411915,
                            "bias_eof": -0.0005092865321712897,
                            "bias_eof_glo": 0.004647601739492968,
                            "cor_cbf": 0.9569795226720145,
                            "cor_cbf_glo": 0.9210195410982632,
                            "cor_eof": 0.9423843939735287,
                            "cor_eof_glo": 0.9057212704672362,
                            "frac_cbf": 0.34347686987956083,
                            "frac_eof": 0.34614745970620986,
                            "rms_cbf": 0.6482144670954418,
                            "rms_cbf_glo": 0.4169075765508977,
                            "rms_eof": 0.6894932471598573,
                            "rms_eof_glo": 0.44023631450675926,
                            "rmsc_cbf": 0.6482142810500351,
                            "rmsc_cbf_glo": 0.4165184503570042,
                            "rmsc_eof": 0.6894930590704104,
                            "rmsc_eof_glo": 0.44021178131504535,
                            "stdv_cbf_pc": 1.4499940856445903,
                            "stdv_eof_pc": 1.5305857613835052,
                            "stdv_pc_ratio_cbf_over_obs": 1.4892310765848857,
                            "stdv_pc_ratio_eof_over_obs": 1.5720035714610217,
                            "tcor_cbf_vs_eof_pc": 0.9913032468112026
                        },
                        "SON": {
                            "bias_cbf": -0.00020275429201959316,
                            "bias_cbf_glo": 0.05824190686717757,
                            "bias_eof": -0.0002793874718429068,
                            "bias_eof_glo": 0.09978564063751692,
                            "cor_cbf": 0.8958374818828689,
                            "cor_cbf_glo": 0.8442432982108105,
                            "cor_eof": 0.7579374783940005,
                            "cor_eof_glo": 0.7316125933783932,
                            "frac_cbf": 0.18730047049863166,
                            "frac_eof": 0.21004466509652572,
                            "rms_cbf": 0.38617682957743615,
                            "rms_cbf_glo": 0.2909183049260787,
                            "rms_eof": 0.6011334631993653,
                            "rms_eof_glo": 0.41214720540237704,
                            "rmsc_cbf": 0.38617677635142333,
                            "rmsc_cbf_glo": 0.2850286659715789,
                            "rmsc_eof": 0.6011333982742127,
                            "rmsc_eof_glo": 0.399885164570467,
                            "stdv_cbf_pc": 0.7747233616597426,
                            "stdv_eof_pc": 0.922711828299419,
                            "stdv_pc_ratio_cbf_over_obs": 1.0515750516957318,
                            "stdv_pc_ratio_eof_over_obs": 1.2524480176581785,
                            "tcor_cbf_vs_eof_pc": 0.8995761702124604
                        },
                        "model_eof_mode": 1
                    }
                }
            },
            "c2": {
                "defaultReference": {
                    "NAM": {
                        "DJF": {
                            "bias_cbf": -0.0006621193496778135,
                            "bias_cbf_glo": 0.05263484459793999,
                            "bias_eof": -0.0007555544407567328,
                            "bias_eof_glo": -0.024830956614754415,
                            "cor_cbf": 0.9400322611939287,
                            "cor_cbf_glo": 0.9249200761807812,
                            "cor_eof": 0.8862842389285965,
                            "cor_eof_glo": 0.8700570590852995,
                            "frac_cbf": 0.33434517434842176,
                            "frac_eof": 0.3484711850326162,
                            "rms_cbf": 0.6481716212772491,
                            "rms_cbf_glo": 0.41658872204013253,
                            "rms_eof": 0.872700267010536,
                            "rms_eof_glo": 0.5379586199016958,
                            "rmsc_cbf": 0.6481712830935542,
                            "rmsc_cbf_glo": 0.4132502104841346,
                            "rmsc_eof": 0.8726999399437058,
                            "rmsc_eof_glo": 0.5373852438615462,
                            "stdv_cbf_pc": 1.7137345165006468,
                            "stdv_eof_pc": 1.8706311341419057,
                            "stdv_pc_ratio_cbf_over_obs": 1.1195063764470885,
                            "stdv_pc_ratio_eof_over_obs": 1.2219999436835303,
                            "tcor_cbf_vs_eof_pc": 0.96482392130436
                        },
                        "JJA": {
                            "bias_cbf": -0.00013974293633987263,
                            "bias_cbf_glo": 0.06687016048559884,
                            "bias_eof": -8.84653705557972e-05,
                            "bias_eof_glo": 0.040573652126167176,
                            "cor_cbf": 0.9240763379474936,
                            "cor_cbf_glo": 0.7167856675770456,
                            "cor_eof": 0.8016748022033681,
                            "cor_eof_glo": 0.6462964496469132,
                            "frac_cbf": 0.1954529417495507,
                            "frac_eof": 0.20988377266546748,
                            "rms_cbf": 0.2405637970769683,
                            "rms_cbf_glo": 0.3167739762213619,
                            "rms_eof": 0.3965827019890366,
                            "rms_eof_glo": 0.35018049164108905,
                            "rmsc_cbf": 0.24056375648879552,
                            "rmsc_cbf_glo": 0.30963548512359207,
                            "rmsc_eof": 0.3965826921220885,
                            "rmsc_eof_glo": 0.347822016955712,
                            "stdv_cbf_pc": 0.5815393704939991,
                            "stdv_eof_pc": 0.6589233510274947,
                            "stdv_pc_ratio_cbf_over_obs": 0.9932164875144404,
                            "stdv_pc_ratio_eof_over_obs": 1.125381305985931,
                            "tcor_cbf_vs_eof_pc": 0.9041649950372739
                        },
                        "MAM": {
                            "bias_cbf": -0.000504836090282448,
                            "bias_cbf_glo": 0.003218620953936213,
                            "bias_eof": -0.0005453522270081194,
                            "bias_eof_glo": 0.002230185410062646,
                            "cor_cbf": 0.9396595615118527,
                            "cor_cbf_glo": 0.8921615649650402,
                            "cor_eof": 0.9155251829557551,
                            "cor_eof_glo": 0.8681055829347071,
                            "frac_cbf": 0.30159826771563264,
                            "frac_eof": 0.30656878985516534,
                            "rms_cbf": 0.5727459924124108,
                            "rms_cbf_glo": 0.38936045967037947,
                            "rms_eof": 0.6389984501716229,
                            "rms_eof_glo": 0.4246880951569857,
                            "rmsc_cbf": 0.5727457699232699,
                            "rmsc_cbf_glo": 0.38934715619082677,
                            "rmsc_eof": 0.6389982174565784,
                            "rmsc_eof_glo": 0.4246822393756368,
                            "stdv_cbf_pc": 1.2975052669131453,
                            "stdv_eof_pc": 1.401033108425823,
                            "stdv_pc_ratio_cbf_over_obs": 1.3326158945404467,
                            "stdv_pc_ratio_eof_over_obs": 1.438945210224445,
                            "tcor_cbf_vs_eof_pc": 0.9852345588846713
                        },
                        "SON": {
                            "bias_cbf": -0.0001267736098927082,
                            "bias_cbf_glo": 0.12932308490982913,
                            "bias_eof": -0.00023097364699049708,
                            "bias_eof_glo": 0.1528390818646074,
                            "cor_cbf": 0.8160073787721789,
                            "cor_cbf_glo": 0.6742958494291389,
                            "cor_eof": 0.6090425084900147,
                            "cor_eof_glo": 0.5157294555110047,
                            "frac_cbf": 0.20657536010743618,
                            "frac_eof": 0.25660111046494966,
                            "rms_cbf": 0.5451586531758859,
                            "rms_cbf_glo": 0.4457668572716137,
                            "rms_eof": 0.84086463874924,
                            "rms_eof_glo": 0.5797118355708311,
                            "rmsc_cbf": 0.545158638435637,
                            "rmsc_cbf_glo": 0.426595394667144,
                            "rmsc_eof": 0.8408646070266392,
                            "rmsc_eof_glo": 0.559201240481176,
                            "stdv_cbf_pc": 0.7682959978458678,
                            "stdv_eof_pc": 1.0569401514514465,
                            "stdv_pc_ratio_cbf_over_obs": 1.0428508337757212,
                            "stdv_pc_ratio_eof_over_obs": 1.4346435765415804,
                            "tcor_cbf_vs_eof_pc": 0.8350183990131097
                        },
                        "model_eof_mode": 1
                    }
                }
            },
            "c3": {
                "defaultReference": {
                    "NAM": {
                        "DJF": {
                            "bias_cbf": -0.0006815889796822638,
                            "bias_cbf_glo": 0.09049677411791626,
                            "bias_eof": -0.0007497949961646434,
                            "bias_eof_glo": 0.0557843731308984,
                            "cor_cbf": 0.9543350836302925,
                            "cor_cbf_glo": 0.930537560890975,
                            "cor_eof": 0.9370090353489237,
                            "cor_eof_glo": 0.9150331530635515,
                            "frac_cbf": 0.37062384778643387,
                            "frac_eof": 0.3750248406472464,
                            "rms_cbf": 0.6563473196085052,
                            "rms_cbf_glo": 0.4514956897198819,
                            "rms_eof": 0.7409363179685987,
                            "rms_eof_glo": 0.48468843716633087,
                            "rmsc_cbf": 0.6563469657077209,
                            "rmsc_cbf_glo": 0.4423332360448203,
                            "rmsc_eof": 0.740935938588707,
                            "rmsc_eof_glo": 0.48146753248493607,
                            "stdv_cbf_pc": 1.8434898057218982,
                            "stdv_eof_pc": 1.9527288905398659,
                            "stdv_pc_ratio_cbf_over_obs": 1.2042697235479825,
                            "stdv_pc_ratio_eof_over_obs": 1.2756307487438083,
                            "tcor_cbf_vs_eof_pc": 0.9897577471587635
                        },
                        "JJA": {
                            "bias_cbf": -0.00012096029072422076,
                            "bias_cbf_glo": 0.04355426855850378,
                            "bias_eof": -0.00011308440905395239,
                            "bias_eof_glo": 0.04040339284178643,
                            "cor_cbf": 0.9184486705787358,
                            "cor_cbf_glo": 0.7729042521650015,
                            "cor_eof": 0.895402733363654,
                            "cor_eof_glo": 0.7638247060501014,
                            "frac_cbf": 0.2807640347344397,
                            "frac_eof": 0.28399821972068895,
                            "rms_cbf": 0.3365274857401562,
                            "rms_cbf_glo": 0.3290399723110087,
                            "rms_eof": 0.3727894105646443,
                            "rms_eof_glo": 0.34176768428053966,
                            "rmsc_cbf": 0.33652746400137845,
                            "rmsc_cbf_glo": 0.3261446443968735,
                            "rmsc_eof": 0.3727893934127571,
                            "rmsc_eof_glo": 0.3393710592630947,
                            "stdv_cbf_pc": 0.7181574853214038,
                            "stdv_eof_pc": 0.7940786566727045,
                            "stdv_pc_ratio_cbf_over_obs": 1.2265478336354327,
                            "stdv_pc_ratio_eof_over_obs": 1.3562143067298782,
                            "tcor_cbf_vs_eof_pc": 0.9858959605160706
                        },
                        "MAM": {
                            "bias_cbf": -0.0005798945763259832,
                            "bias_cbf_glo": 0.0793834244472288,
                            "bias_eof": -0.0005825613193830151,
                            "bias_eof_glo": 0.09916032967991713,
                            "cor_cbf": 0.9492335111169611,
                            "cor_cbf_glo": 0.9097274345630251,
                            "cor_eof": 0.9390850577618135,
                            "cor_eof_glo": 0.900398149307574,
                            "frac_cbf": 0.3589808631750554,
                            "frac_eof": 0.36057951823756346,
                            "rms_cbf": 0.7099381335287005,
                            "rms_cbf_glo": 0.46628448228987773,
                            "rms_eof": 0.7383139829271778,
                            "rms_eof_glo": 0.4861654695533489,
                            "rmsc_cbf": 0.7099378966927286,
                            "rmsc_cbf_glo": 0.4594774100512129,
                            "rmsc_eof": 0.7383137530942399,
                            "rmsc_eof_glo": 0.4759454725110833,
                            "stdv_cbf_pc": 1.4852598739563276,
                            "stdv_eof_pc": 1.5777336889174018,
                            "stdv_pc_ratio_cbf_over_obs": 1.5254511608004404,
                            "stdv_pc_ratio_eof_over_obs": 1.6204273268233322,
                            "tcor_cbf_vs_eof_pc": 0.9942248169119879
                        },
                        "SON": {
                            "bias_cbf": -0.00022358962427084658,
                            "bias_cbf_glo": 0.1199536156334667,
                            "bias_eof": -0.00027539079105188896,
                            "bias_eof_glo": 0.1153419922406255,
                            "cor_cbf": 0.8669145426282209,
                            "cor_cbf_glo": 0.6888159081775223,
                            "cor_eof": 0.7271895355462034,
                            "cor_eof_glo": 0.6051645577380352,
                            "frac_cbf": 0.2392630873662037,
                            "frac_eof": 0.2728503358418847,
                            "rms_cbf": 0.5122354619700629,
                            "rms_cbf_glo": 0.4584193282279459,
                            "rms_eof": 0.7337630065945615,
                            "rms_eof_glo": 0.5279303536853092,
                            "rmsc_cbf": 0.512235413171877,
                            "rmsc_cbf_glo": 0.4424470709468193,
                            "rmsc_eof": 0.7337629549156885,
                            "rmsc_eof_glo": 0.5151763612281324,
                            "stdv_cbf_pc": 0.8632668386058948,
                            "stdv_eof_pc": 1.0711106767574825,
                            "stdv_pc_ratio_cbf_over_obs": 1.1717600312057,
                            "stdv_pc_ratio_eof_over_obs": 1.45387801765786,
                            "tcor_cbf_vs_eof_pc": 0.8991424563075172
                        },
                        "model_eof_mode": 1
                    }
                }
            }
        }
    },
    "json_structure": [
        "model",
        "realization",
        "reference",
        "mode",
        "season",
        "statistic"
    ],
    "json_version": 3.0,
    "provenance": {
        "commandLine": "variability_modes_driver.py -p myParam_NAM_cmip5_GFDL-CM3.py",
        "conda": {},
        "date": "2019-03-13 16:49:09",
        "openGL": {
            "GLX": {
                "client": {},
                "server": {}
            }
        },
        "osAccess": false,
        "packages": {},
        "platform": {
            "Name": "crunchy.llnl.gov",
            "OS": "Linux",
            "Version": "2.6.32-754.10.1.el6.x86_64"
        },
        "userId": "lee1043"
    }
}